{
  "version": "7",
  "dialect": "postgresql",
  "entries": [
    {
      "idx": 0,
      "version": "7",
      "when": 1778666404261,
      "tag": "0000_outstanding_punisher",
      "breakpoints": true
    },
    {
      "idx": 1,
      "version": "7",
      "when": 1778733869797,
      "tag": "0001_mute_the_professor",
      "breakpoints": true
    },
    {
      "idx": 2,
      "version": "7",
      "when": 1778736990207,
      "tag": "0002_familiar_husk",
      "breakpoints": true
    },
    {
      "idx": 3,
      "version": "7",
      "when": 1778749549150,
      "tag": "0003_square_radioactive_man",
      "breakpoints": true
    },
    {
      "idx": 4,
      "version": "7",
      "when": 1778819867831,
      "tag": "0004_aberrant_ironclad",
      "breakpoints": true
    },
    {
      "idx": 5,
      "version": "7",
      "when": 1778830979942,
      "tag": "0005_real_jack_flag",
      "breakpoints": true
    }
  ]
}